{
	"Benefit1" :  
	{
		"Image" : "abcdefg",
		"Summary" : "Exclusive single point of contact"
	},
	
	"Benefit2" :  
	{
		"Image" : "hijklmn",
		"Summary" : "Highest standards of Quality Assurance"
	},
	
	"Benefit3" :  
	{
		"Image" : "opqrstu",
		"Summary" : "Seasoned Professionals"
	},
	
	"Benefit4" :  
	{
		"Image" : "abcdefg",
		"Summary" : "Platform-agnostic approach"
	},
	
	"Benefit5" :  
	{
		"Image" : "hijklmn",
		"Summary" : "Industry grade best practices"
	},
	
	"Benefit6s" :  
	{
		"Image" : "opqrstu",
		"Summary" : "Competent cost offering"
	}	
}
